envpy/__init__.py
envpy/error.py
envpy/variables.py
external_variables-0.2.1.dist-info/LICENSE
external_variables-0.2.1.dist-info/METADATA
external_variables-0.2.1.dist-info/WHEEL
external_variables-0.2.1.dist-info/top_level.txt
external_variables-0.2.1.dist-info/RECORD
