Metadata-Version: 2.1
Name: external-variables
Version: 0.2.1
Summary: A simple way to use enviroment configurations.
Home-page: https://github.com/Combofoods/pyenv
Author: Davi Mello
Author-email: dsmello.9@gmail.com
License: GPL
Platform: UNKNOWN
Classifier: Programming Language :: Python :: 3
Classifier: License :: OSI Approved :: MIT License
Classifier: Operating System :: OS Independent
